instacart_order_history_download.py
instacart_order_history_download-1.0.0.dist-info/licenses/LICENSE
instacart_order_history_download-1.0.0.dist-info/METADATA
instacart_order_history_download-1.0.0.dist-info/WHEEL
instacart_order_history_download-1.0.0.dist-info/entry_points.txt
instacart_order_history_download-1.0.0.dist-info/top_level.txt
instacart_order_history_download-1.0.0.dist-info/RECORD
