Metadata-Version: 2.4
Name: instacart-order-history-download
Version: 1.0.0
Summary: A command-line tool to download your Instacart order history
Author-email: Mike Vincent <michael.thomas.vincent@gmail.com>
License-Expression: GPL-3.0-only
Project-URL: Homepage, https://mike-vincent.github.io/instacart-order-history-download
Project-URL: Repository, https://github.com/mike-vincent/instacart-order-history-download
Project-URL: Issues, https://github.com/mike-vincent/instacart-order-history-download/issues
Keywords: instacart,receipts,orders,cli
Classifier: Development Status :: 5 - Production/Stable
Classifier: Environment :: Console
Classifier: Intended Audience :: End Users/Desktop
Classifier: Operating System :: OS Independent
Classifier: Programming Language :: Python :: 3
Classifier: Programming Language :: Python :: 3.8
Classifier: Programming Language :: Python :: 3.9
Classifier: Programming Language :: Python :: 3.10
Classifier: Programming Language :: Python :: 3.11
Classifier: Programming Language :: Python :: 3.12
Classifier: Topic :: Utilities
Requires-Python: >=3.8
License-File: LICENSE
Dynamic: license-file
